{
  "Ns": [
    100,
    1000
  ],
  "caps": [
    0,
    16,
    64,
    256,
    1024
  ],
  "cli_argv": [
    "experiments/X7_forget_merge/run.py",
    "--out",
    "runs/X7_full_v1",
    "--Ns",
    "100",
    "1000",
    "--caps",
    "0",
    "16",
    "64",
    "256",
    "1024",
    "--policies",
    "lru",
    "fifo",
    "--seeds",
    "0",
    "1",
    "2",
    "--alphas",
    "0.0",
    "1.0",
    "--read-period",
    "32"
  ],
  "commit": "054b4abb394a2f090932fa6690e12cadf411b1ad",
  "dataset_sha1": {
    "distractors.jsonl": "135946c01b78244dd4d038827ddf17114cda4ebf",
    "facts.jsonl": "6b6140fc641186208b6fa27d3ab86748473bca94"
  },
  "device": "mps",
  "dirty": true,
  "dirty_diff_sha1": "da39a3ee5e6b4b0d3255bfef95601890afd80709",
  "dtype": "bf16",
  "host": "xiaogatongzhideMacBook-Pro.local",
  "model": "google/gemma-3-1b-it",
  "mps_available": true,
  "numpy": "2.4.1",
  "policies": [
    "lru",
    "fifo"
  ],
  "prereg_version": "X7.v1",
  "python": "3.14.0",
  "read_period": 32,
  "started_at": "2026-05-06T03:50:47Z",
  "torch": "2.10.0",
  "transformers": "5.2.0"
}
